<?xml version="1.0" encoding="UTF-8"?>
<!DOCTYPE para PUBLIC "-//OASIS//DTD DocBook XML V4.5//EN"
   "http://www.oasis-open.org/docbook/xml/4.5/docbookx.dtd" >


<para>Como acontece com a maioria das bibliotecas, não existe configuração a se
fazer, exceto o diretório da biblioteca, ou seja, <filename
class="directory">/opt/lib</filename> ou <filename
class="directory">/usr/local/lib</filename> deveria aparecer em
<filename>/etc/ld.so.conf</filename> de forma que o <command>ldd</command>
consiga encontrar as bibliotecas compartilhadas. Depois de verificar se esse
é o caso, <command>/sbin/ldconfig</command> deveria ser executado enquanto
logado(a) como <systemitem class="username">root</systemitem>.</para>
